zhixuewang/__init__.py
zhixuewang/account.py
zhixuewang/exceptions.py
zhixuewang/models.py
zhixuewang/session.py
zhixuewang/urls.py
zhixuewang/student/__init__.py
zhixuewang/student/student.py
zhixuewang/student/urls.py
zhixuewang/teacher/__init__.py
zhixuewang/teacher/models.py
zhixuewang/teacher/teacher.py
zhixuewang/teacher/urls.py
zhixuewang/tools/__init__.py
zhixuewang/tools/datetime_tool.py
zhixuewang-1.3.4.dist-info/LICENSE
zhixuewang-1.3.4.dist-info/METADATA
zhixuewang-1.3.4.dist-info/WHEEL
zhixuewang-1.3.4.dist-info/top_level.txt
zhixuewang-1.3.4.dist-info/RECORD
