Metadata-Version: 2.1
Name: zhixuewang
Version: 1.3.4
Summary: 智学网的api
Author: anwenhu,MasterYuan418,immoses648,krn1pnc,Haorwen,amakerlife
Author-email: anemailpocket@163.com
License: MIT
Keywords: 智学网,zhixue,zhixuewang
Platform: any
License-File: LICENSE
Requires-Dist: requests
Requires-Dist: playwright
